i3pyblocks/__init__.py
i3pyblocks/__main__.py
i3pyblocks/__version__.py
i3pyblocks/cli.py
i3pyblocks/core.py
i3pyblocks/formatter.py
i3pyblocks/types.py
i3pyblocks/utils.py
i3pyblocks/_internal/__init__.py
i3pyblocks/_internal/logger.py
i3pyblocks/_internal/misc.py
i3pyblocks/_internal/models.py
i3pyblocks/_internal/subprocess.py
i3pyblocks/blocks/__init__.py
i3pyblocks/blocks/base.py
i3pyblocks/blocks/basic.py
i3pyblocks/blocks/datetime.py
i3pyblocks/blocks/dbus.py
i3pyblocks/blocks/http.py
i3pyblocks/blocks/i3ipc.py
i3pyblocks/blocks/inotify.py
i3pyblocks/blocks/ps.py
i3pyblocks/blocks/pulse.py
i3pyblocks/blocks/shell.py
i3pyblocks/blocks/x11.py
i3pyblocks-2020.10.3.dist-info/LICENSE
i3pyblocks-2020.10.3.dist-info/METADATA
i3pyblocks-2020.10.3.dist-info/WHEEL
i3pyblocks-2020.10.3.dist-info/entry_points.txt
i3pyblocks-2020.10.3.dist-info/top_level.txt
i3pyblocks-2020.10.3.dist-info/RECORD
