Metadata-Version: 2.1
Name: i3pyblocks
Version: 2020.10.3
Summary: A replacement for i3status, written in Python using asyncio.
Home-page: https://i3pyblocks.readthedocs.io
Author: Thiago Kenji Okada
Author-email: thiagokokada@gmail.com
License: UNKNOWN
Project-URL: Documentation, https://i3pyblocks.readthedocs.io
Project-URL: Source, https://github.com/thiagokokada/i3pyblocks
Platform: UNKNOWN
Classifier: Development Status :: 4 - Beta
Classifier: Programming Language :: Python :: 3
Classifier: Programming Language :: Python :: 3.6
Classifier: Programming Language :: Python :: 3.7
Classifier: Programming Language :: Python :: 3.8
Classifier: License :: OSI Approved :: MIT License
Classifier: Operating System :: POSIX
Requires-Python: >=3.6
Provides-Extra: blocks.dbus
Requires-Dist: dbus-next (>=0.1.1) ; extra == 'blocks.dbus'
Provides-Extra: blocks.http
Requires-Dist: aiohttp (>=3.4.0) ; extra == 'blocks.http'
Provides-Extra: blocks.i3ipc
Requires-Dist: i3ipc (>=2.0.1) ; extra == 'blocks.i3ipc'
Provides-Extra: blocks.inotify
Requires-Dist: aionotify (>=0.2.0) ; extra == 'blocks.inotify'
Provides-Extra: blocks.ps
Requires-Dist: psutil (>=5.4.8) ; extra == 'blocks.ps'
Provides-Extra: blocks.pulse
Requires-Dist: pulsectl (>=18.10.5) ; extra == 'blocks.pulse'
Provides-Extra: blocks.x11
Requires-Dist: python-xlib (>=0.2.8) ; extra == 'blocks.x11'
Provides-Extra: dev
Requires-Dist: black ; extra == 'dev'
Requires-Dist: flake8 ; extra == 'dev'
Requires-Dist: flake8-bugbear ; extra == 'dev'
Requires-Dist: isort ; extra == 'dev'
Requires-Dist: mypy ; extra == 'dev'
Requires-Dist: pip-tools ; extra == 'dev'
Provides-Extra: docs
Requires-Dist: sphinx ; extra == 'docs'
Requires-Dist: sphinx-autoapi ; extra == 'docs'
Requires-Dist: sphinx-rtd-theme ; extra == 'docs'
Provides-Extra: test
Requires-Dist: asynctest ; extra == 'test'
Requires-Dist: pytest ; extra == 'test'
Requires-Dist: pytest-aiohttp ; extra == 'test'
Requires-Dist: pytest-asyncio ; extra == 'test'
Requires-Dist: pytest-cov ; extra == 'test'
